backup/__init__.py
backup/backup.py
backup/errors.py
backup/incremental_backup.py
backup/rsync_copy.py
backup.py-0.1.1.data/scripts/pybackup
backup.py-0.1.1.dist-info/LICENSE.txt
backup.py-0.1.1.dist-info/METADATA
backup.py-0.1.1.dist-info/WHEEL
backup.py-0.1.1.dist-info/top_level.txt
backup.py-0.1.1.dist-info/RECORD
