Metadata-Version: 2.1
Name: backup.py
Version: 0.1.1
Summary: Recursive and Incremental backup utility
Home-page: http://github.com/harsh8398/backup.py
Author: Harsh Patel
Author-email: pharsh58@gmail.com
License: UNKNOWN
Platform: UNKNOWN
Classifier: Programming Language :: Python
Classifier: Programming Language :: Python :: 3
Classifier: Programming Language :: Python :: 3.5
Classifier: Programming Language :: Python :: 3.6
Classifier: Programming Language :: Python :: 3.7
Classifier: License :: OSI Approved :: MIT License
Classifier: Operating System :: OS Independent
Requires-Python: >=3.5
Requires-Dist: tqdm
